Metadata-Version: 2.4
Name: meu_investimento_josemarinho
Version: 0.1
Summary: Uma biblioteca para cálculos de investimentos
Home-page: https://github.com/jusemarinho/meu_investimento
Author: José Paulo Marinho
Author-email: josepaulomarinho2@gmail.com
Classifier: Programming Language :: Python :: 3
Classifier: License :: OSI Approved :: MIT License
Classifier: Operating System :: OS Independent
Requires-Python: >=3.6
License-File: LICENSE
Dynamic: author
Dynamic: author-email
Dynamic: classifier
Dynamic: description
Dynamic: description-content-type
Dynamic: home-page
Dynamic: license-file
Dynamic: requires-python
Dynamic: summary
